aquaui/__init__.py
aquaui/alert.py
aquaui/choice.py
aquaui/color_picker.py
aquaui/dialog.py
aquaui/notification/fallback_notification.py
aquaui/notification/native_notification.py
aquaui/types/buttons.py
aquaui/types/result.py
aquaui/utils.py
aquaui-0.0.1.post2.dist-info/LICENSE
aquaui-0.0.1.post2.dist-info/WHEEL
aquaui-0.0.1.post2.dist-info/METADATA
aquaui-0.0.1.post2.dist-info/RECORD
