Metadata-Version: 2.1
Name: aquaui
Version: 0.0.1.post2
Summary: Native Mac OS UI elements with python
Home-page: https://github.com/ninest/aquaui/
License: MIT
Author: ninest
Requires-Python: >=3.7,<4.0
Classifier: License :: OSI Approved :: MIT License
Classifier: Programming Language :: Python :: 3
Classifier: Programming Language :: Python :: 3.7
Classifier: Programming Language :: Python :: 3.8
Classifier: Programming Language :: Python :: 3.9
Project-URL: Documentation, https://github.com/ninest/aquaui/
Project-URL: Repository, https://github.com/ninest/aquaui/
